.coveragerc
AUTHORS
LICENSE
MAINTAINERS
MANIFEST.in
README.rst
pytest.ini
run-tests.sh
setup.cfg
setup.py
Flask_Sitemap_Domain.egg-info/PKG-INFO
Flask_Sitemap_Domain.egg-info/SOURCES.txt
Flask_Sitemap_Domain.egg-info/dependency_links.txt
Flask_Sitemap_Domain.egg-info/not-zip-safe
Flask_Sitemap_Domain.egg-info/requires.txt
Flask_Sitemap_Domain.egg-info/top_level.txt
docs/Makefile
docs/conf.py
docs/index.rst
docs/requirements.txt
flask_sitemap_domain/__init__.py
flask_sitemap_domain/config.py
flask_sitemap_domain/script.py
flask_sitemap_domain/version.py
flask_sitemap_domain/templates/flask_sitemap_domain/sitemap.xml
flask_sitemap_domain/templates/flask_sitemap_domain/sitemapindex.xml
tests/__init__.py
tests/helpers.py
tests/test_ext.py
tests/data/sitemap.xml